gamma_cloudinary/__init__.py
gamma_cloudinary/apps.py
gamma_cloudinary/config.py
gamma_cloudinary/storage.py
gamma_cloudinary/utils.py
gamma_cloudinary/templatetags/__init__.py
gamma_cloudinary/templatetags/gamma_cloudinary_static.py
tests/__init__.py
tests/helpers.py
tests/test_cloudinary_initialization.py
tests/test_cloudinary_storage.py
tests/test_helpers.py
tests/test_static_cloudinary_storage.py
tests/test_template_tags.py
tests/settings/__init__.py
tests/settings/staging.py
tests/static/css/LICENSE
tests/static/css/bar.css
tests/static/css/empty.css
tests/static/css/foo.css
tests/static/css/oswald-fonts.css
tests/static/css/unmodified.css
tests/static/fonts/Oswald/OFL.txt
tests/static/fonts/Oswald/Oswald-Bold.woff
tests/static/fonts/Oswald/Oswald-Bold.woff2
tests/static/fonts/Oswald/Oswald-ExtraLight.woff
tests/static/fonts/Oswald/Oswald-ExtraLight.woff2
tests/static/fonts/Oswald/Oswald-Light.woff
tests/static/fonts/Oswald/Oswald-Light.woff2
tests/static/fonts/Oswald/Oswald-Medium.woff
tests/static/fonts/Oswald/Oswald-Medium.woff2
tests/static/fonts/Oswald/Oswald-Regular.woff
tests/static/fonts/Oswald/Oswald-Regular.woff2
tests/static/fonts/Oswald/Oswald-SemiBold.woff
tests/static/fonts/Oswald/Oswald-SemiBold.woff2
tests/static/fonts/Oswald/README.txt
tests/static/fonts/Oswald/demo.html
tests/static/fonts/Oswald/stylesheet.css
tests/static/fonts/Roboto/LICENSE.txt
tests/static/fonts/Roboto/Roboto-Black.ttf
tests/static/fonts/Roboto/Roboto-BlackItalic.ttf
tests/static/fonts/Roboto/Roboto-Bold.ttf
tests/static/fonts/Roboto/Roboto-BoldItalic.ttf
tests/static/fonts/Roboto/Roboto-Italic.ttf
tests/static/fonts/Roboto/Roboto-Light.ttf
tests/static/fonts/Roboto/Roboto-LightItalic.ttf
tests/static/fonts/Roboto/Roboto-Medium.ttf
tests/static/fonts/Roboto/Roboto-MediumItalic.ttf
tests/static/fonts/Roboto/Roboto-Regular.ttf
tests/static/fonts/Roboto/Roboto-Thin.ttf
tests/static/fonts/Roboto/Roboto-ThinItalic.ttf
tests/static/images/placeholder.png
tests/static/js/bar.js
django_gamma_cloudinary-0.2.3.dist-info/AUTHORS
django_gamma_cloudinary-0.2.3.dist-info/LICENSE
django_gamma_cloudinary-0.2.3.dist-info/METADATA
django_gamma_cloudinary-0.2.3.dist-info/WHEEL
django_gamma_cloudinary-0.2.3.dist-info/top_level.txt
django_gamma_cloudinary-0.2.3.dist-info/RECORD
