Metadata-Version: 2.1
Name: django-gamma-cloudinary
Version: 0.2.3
Summary: A Django storage backend to integrate with Cloudinary for static files and media storage.
Home-page: https://github.com/barakaVictor/django-gamma-cloudinary
Author: Victor Baraka Oyuga
Author-email: barakavictor62@gmail.com
License: BSD 3-Clause License
Platform: UNKNOWN
Classifier: Environment :: Web Environment
Classifier: Framework :: Django
Classifier: Framework :: Django :: 3.1
Classifier: Intended Audience :: Developers
Classifier: License :: OSI Approved :: BSD License
Classifier: Operating System :: OS Independent
Classifier: Programming Language :: Python
Classifier: Programming Language :: Python :: 3
Classifier: Programming Language :: Python :: 3 :: Only
Classifier: Programming Language :: Python :: 3.6
Classifier: Programming Language :: Python :: 3.7
Classifier: Programming Language :: Python :: 3.8
Classifier: Topic :: Internet :: WWW/HTTP
Classifier: Topic :: Internet :: WWW/HTTP :: Dynamic Content
License-File: LICENSE
License-File: AUTHORS
Requires-Dist: Django (>=3.1)
Requires-Dist: cloudinary (>=1.24.0)
Requires-Dist: requests (>=2.10.0)
Requires-Dist: python-magic (>=0.4.22)
